README
setup.py
FancyQt.egg-info/PKG-INFO
FancyQt.egg-info/SOURCES.txt
FancyQt.egg-info/dependency_links.txt
FancyQt.egg-info/namespace_packages.txt
FancyQt.egg-info/requires.txt
FancyQt.egg-info/top_level.txt
fancyqt/__init__.py
fancyqt/firefox.py
fancyqt/firefox_rc.py