Metadata-Version: 1.1
Name: FancyQt
Version: 1.0.1
Summary: Modern stylesheets for Qt 4.x.
Home-page: https://github.com/datalyze-solutions/FancyQt
Author: Matthias Ludwig
Author-email: m.Ludwig@datalyze-solutions.com
License: MIT License
Platform: any
Classifier: Programming Language :: Python
Classifier: Development Status :: 4 - Beta
Classifier: Natural Language :: German
Classifier: Environment :: X11 Applications :: Qt
Classifier: Intended Audience :: Developers
Classifier: License :: OSI Approved :: BSD License
Classifier: Operating System :: OS Independent
Classifier: Topic :: Software Development :: Libraries :: Python Modules
Classifier: Topic :: Software Development :: User Interfaces
